a1_sqladb_a1ptfl/__init__.py
a1_sqladb_a1ptfl/__main__.py
a1_sqladb_a1ptfl/cli.py
a1_sqladb_a1ptfl/sqladb_a1ptfl.py
a1_sqladb_a1ptfl-0.1.0.dist-info/entry_points.txt
a1_sqladb_a1ptfl-0.1.0.dist-info/METADATA
a1_sqladb_a1ptfl-0.1.0.dist-info/WHEEL
a1_sqladb_a1ptfl-0.1.0.dist-info/RECORD
